tibbtech/__init__.py
tibbtech/neuroai.py
tibbtech-0.1.3.dist-info/METADATA
tibbtech-0.1.3.dist-info/WHEEL
tibbtech-0.1.3.dist-info/top_level.txt
tibbtech-0.1.3.dist-info/RECORD
