Metadata-Version: 2.4
Name: tibbtech
Version: 0.1.3
Summary: TibbTech NeuroAI tools
Author: Tibbtech
Author-email: tibbtech <taharazzaq091@gmail.com>
License: MIT
Project-URL: Homepage, https://github.com/yourusername/tibbtech
Keywords: neuroai,ai,winner-take-all
Requires-Python: >=3.7
Dynamic: author
Dynamic: requires-python
